pytidespy3/__init__.py
pytidespy3/astro.py
pytidespy3/constituent.py
pytidespy3/nodal_corrections.py
pytidespy3/tide.py
pytides_py3-0.0.6.dist-info/AUTHORS
pytides_py3-0.0.6.dist-info/COPYING
pytides_py3-0.0.6.dist-info/METADATA
pytides_py3-0.0.6.dist-info/WHEEL
pytides_py3-0.0.6.dist-info/top_level.txt
pytides_py3-0.0.6.dist-info/RECORD
