Metadata-Version: 2.1
Name: pytides-py3
Version: 0.0.6
Summary: Tidal analysis and prediction library for Python >= 3.10.x
Home-page: https://github.com/sigmadream/pytides-py3
Author: Sangkon Han
Author-email: sigmadream@gmail.com
License: MIT
Platform: UNKNOWN
Classifier: Programming Language :: Python :: 3
Classifier: License :: OSI Approved :: MIT License
Classifier: Operating System :: OS Independent
Requires-Python: >=3.10
License-File: COPYING
License-File: AUTHORS
Requires-Dist: numpy (>=1.8)
Requires-Dist: scipy (>=0.11)
